<Annotation>
  <folder>data_images</folder>
  <filename>FLIR_07820.jpeg</filename>
  <path>D:\IR_RGB\yolo_object_detection\Notes\1_datapreparation\data_images</path>
  <source>
	<database>Unknown</database>
  </source>
  <size>
    <width>640</width>
    <height>512</height>
    <depth>3</depth>
  </size>
  <object>
    <name>person</name>
    <difficult>0</difficult>
    <bndbox>
      <xmin>462</xmin>
      <ymin>220</ymin>
      <xmax>484</xmax>
      <ymax>286</ymax>
    </bndbox>
  </object>
  <object>
    <name>car</name>
    <difficult>0</difficult>
    <bndbox>
      <xmin>411</xmin>
      <ymin>229</ymin>
      <xmax>462</xmax>
      <ymax>267</ymax>
    </bndbox>
  </object>
  <object>
    <name>car</name>
    <difficult>0</difficult>
    <bndbox>
      <xmin>392</xmin>
      <ymin>229</ymin>
      <xmax>411</xmax>
      <ymax>255</ymax>
    </bndbox>
  </object>
  <object>
    <name>car</name>
    <difficult>0</difficult>
    <bndbox>
      <xmin>345</xmin>
      <ymin>230</ymin>
      <xmax>389</xmax>
      <ymax>264</ymax>
    </bndbox>
  </object>
  <object>
    <name>car</name>
    <difficult>0</difficult>
    <bndbox>
      <xmin>262</xmin>
      <ymin>223</ymin>
      <xmax>311</xmax>
      <ymax>260</ymax>
    </bndbox>
  </object>
  <object>
    <name>car</name>
    <difficult>0</difficult>
    <bndbox>
      <xmin>224</xmin>
      <ymin>228</ymin>
      <xmax>242</xmax>
      <ymax>252</ymax>
    </bndbox>
  </object>
  <object>
    <name>car</name>
    <difficult>0</difficult>
    <bndbox>
      <xmin>177</xmin>
      <ymin>224</ymin>
      <xmax>224</xmax>
      <ymax>260</ymax>
    </bndbox>
  </object>
  <object>
    <name>person</name>
    <difficult>0</difficult>
    <bndbox>
      <xmin>251</xmin>
      <ymin>220</ymin>
      <xmax>263</xmax>
      <ymax>249</ymax>
    </bndbox>
  </object>
  <object>
    <name>car</name>
    <difficult>0</difficult>
    <bndbox>
      <xmin>485</xmin>
      <ymin>237</ymin>
      <xmax>639</xmax>
      <ymax>459</ymax>
    </bndbox>
  </object>
  <object>
    <name>car</name>
    <difficult>0</difficult>
    <bndbox>
      <xmin>321</xmin>
      <ymin>226</ymin>
      <xmax>344</xmax>
      <ymax>242</ymax>
    </bndbox>
  </object>
</Annotation>
