<Annotation>
  <folder>data_images</folder>
  <filename>FLIR_03824.jpeg</filename>
  <path>D:\IR_RGB\yolo_object_detection\Notes\1_datapreparation\data_images</path>
  <source>
	<database>Unknown</database>
  </source>
  <size>
    <width>640</width>
    <height>512</height>
    <depth>3</depth>
  </size>
  <object>
    <name>bicycle</name>
    <difficult>0</difficult>
    <bndbox>
      <xmin>451</xmin>
      <ymin>218</ymin>
      <xmax>485</xmax>
      <ymax>254</ymax>
    </bndbox>
  </object>
  <object>
    <name>bicycle</name>
    <difficult>0</difficult>
    <bndbox>
      <xmin>410</xmin>
      <ymin>220</ymin>
      <xmax>438</xmax>
      <ymax>252</ymax>
    </bndbox>
  </object>
  <object>
    <name>car</name>
    <difficult>0</difficult>
    <bndbox>
      <xmin>338</xmin>
      <ymin>204</ymin>
      <xmax>394</xmax>
      <ymax>240</ymax>
    </bndbox>
  </object>
  <object>
    <name>car</name>
    <difficult>0</difficult>
    <bndbox>
      <xmin>242</xmin>
      <ymin>207</ymin>
      <xmax>268</xmax>
      <ymax>222</ymax>
    </bndbox>
  </object>
  <object>
    <name>car</name>
    <difficult>0</difficult>
    <bndbox>
      <xmin>333</xmin>
      <ymin>213</ymin>
      <xmax>341</xmax>
      <ymax>234</ymax>
    </bndbox>
  </object>
</Annotation>
